kimm/__init__.py
kimm/_src/kimm_export.py
kimm/_src/version.py
kimm/_src/blocks/__init__.py
kimm/_src/blocks/conv2d.py
kimm/_src/blocks/depthwise_separation.py
kimm/_src/blocks/inverted_residual.py
kimm/_src/blocks/squeeze_and_excitation.py
kimm/_src/blocks/transformer.py
kimm/_src/export/__init__.py
kimm/_src/export/export_onnx.py
kimm/_src/export/export_onnx_test.py
kimm/_src/export/export_tflite.py
kimm/_src/export/export_tflite_test.py
kimm/_src/layers/__init__.py
kimm/_src/layers/attention.py
kimm/_src/layers/attention_test.py
kimm/_src/layers/layer_scale.py
kimm/_src/layers/layer_scale_test.py
kimm/_src/layers/learnable_affine.py
kimm/_src/layers/learnable_affine_test.py
kimm/_src/layers/position_embedding.py
kimm/_src/layers/position_embedding_test.py
kimm/_src/layers/reparameterizable_conv2d.py
kimm/_src/layers/reparameterizable_conv2d_test.py
kimm/_src/models/__init__.py
kimm/_src/models/base_model.py
kimm/_src/models/convmixer.py
kimm/_src/models/convnext.py
kimm/_src/models/densenet.py
kimm/_src/models/efficientnet.py
kimm/_src/models/ghostnet.py
kimm/_src/models/ghostnet_v3.py
kimm/_src/models/hgnet.py
kimm/_src/models/inception_next.py
kimm/_src/models/inception_v3.py
kimm/_src/models/mobilenet_v2.py
kimm/_src/models/mobilenet_v3.py
kimm/_src/models/mobileone.py
kimm/_src/models/mobilevit.py
kimm/_src/models/models_test.py
kimm/_src/models/regnet.py
kimm/_src/models/repvgg.py
kimm/_src/models/resnet.py
kimm/_src/models/vgg.py
kimm/_src/models/vision_transformer.py
kimm/_src/models/xception.py
kimm/_src/utils/__init__.py
kimm/_src/utils/make_divisble.py
kimm/_src/utils/model_registry.py
kimm/_src/utils/model_registry_test.py
kimm/_src/utils/model_utils.py
kimm/_src/utils/model_utils_test.py
kimm/_src/utils/module_utils.py
kimm/_src/utils/timm_utils.py
kimm/blocks/__init__.py
kimm/export/__init__.py
kimm/layers/__init__.py
kimm/models/__init__.py
kimm/models/base_model/__init__.py
kimm/models/convmixer/__init__.py
kimm/models/convnext/__init__.py
kimm-0.2.5.dist-info/LICENSE
kimm-0.2.5.dist-info/METADATA
kimm-0.2.5.dist-info/WHEEL
kimm-0.2.5.dist-info/top_level.txt
kimm-0.2.5.dist-info/RECORD
