Metadata-Version: 2.1
Name: kimm
Version: 0.2.5
Summary: A Keras model zoo with pretrained weights.
Author-email: Hong-Yu Chiu <james77777778@gmail.com>
Maintainer-email: Hong-Yu Chiu <james77777778@gmail.com>
License: Apache License 2.0
Project-URL: Homepage, https://github.com/james77777778/keras-image-models
Project-URL: Documentation, https://github.com/james77777778/keras-image-models
Project-URL: Repository, https://github.com/james77777778/keras-image-models.git
Project-URL: Issues, https://github.com/james77777778/keras-image-models/issues
Keywords: deep-learning,model-zoo,keras,jax,tensorflow,torch,imagenet,pretrained-weights,timm
Classifier: Programming Language :: Python
Classifier: Programming Language :: Python :: 3
Classifier: Programming Language :: Python :: 3.9
Classifier: Programming Language :: Python :: 3.10
Classifier: Programming Language :: Python :: 3.11
Classifier: Programming Language :: Python :: 3.12
Classifier: Programming Language :: Python :: 3 :: Only
Classifier: Operating System :: Unix
Classifier: Operating System :: MacOS
Classifier: Intended Audience :: Science/Research
Classifier: Topic :: Scientific/Engineering
Classifier: Topic :: Software Development
Requires-Python: >=3.9
License-File: LICENSE
Requires-Dist: keras
Provides-Extra: examples
Requires-Dist: opencv-python ; extra == 'examples'
Requires-Dist: matplotlib ; extra == 'examples'
Provides-Extra: tests
Requires-Dist: tf2onnx ; extra == 'tests'
Requires-Dist: onnx ; extra == 'tests'
Requires-Dist: onnxoptimizer ; extra == 'tests'
Requires-Dist: onnxsim ; extra == 'tests'
Requires-Dist: isort ; extra == 'tests'
Requires-Dist: ruff ; extra == 'tests'
Requires-Dist: black ; extra == 'tests'
Requires-Dist: pytest ; extra == 'tests'
Requires-Dist: pytest-cov ; extra == 'tests'
Requires-Dist: coverage ; extra == 'tests'
Requires-Dist: pre-commit ; extra == 'tests'
Requires-Dist: namex ; extra == 'tests'
